fcs/__init__.py
fcs/fcs.py
fcsx-0.0.1.dist-info/LICENSE
fcsx-0.0.1.dist-info/WHEEL
fcsx-0.0.1.dist-info/METADATA
fcsx-0.0.1.dist-info/RECORD
