Metadata-Version: 2.1
Name: fcsx
Version: 0.0.1
Summary: FCS for Humans
Home-page: https://github.com/imyizhang/fcsx/
License: BSD-3-Clause
Author: Yi Zhang
Author-email: yizhang.dev@gmail.com
Requires-Python: >=3.10,<4.0
Classifier: License :: OSI Approved :: BSD License
Classifier: Programming Language :: Python :: 3
Classifier: Programming Language :: Python :: 3.10
Provides-Extra: numpy
Requires-Dist: numpy (>=1.22.4,<2.0.0); extra == "numpy"
Project-URL: Documentation, https://fcsx.readthedocs.io/en/latest/
Project-URL: Repository, https://github.com/imyizhang/fcsx/
